README.md
setup.py
pivotal_fetcher/__init__.py
pivotal_fetcher.egg-info/PKG-INFO
pivotal_fetcher.egg-info/SOURCES.txt
pivotal_fetcher.egg-info/dependency_links.txt
pivotal_fetcher.egg-info/entry_points.txt
pivotal_fetcher.egg-info/requires.txt
pivotal_fetcher.egg-info/top_level.txt