Metadata-Version: 1.1
Name: pivotal-fetcher
Version: 4.0
Summary: Fetches Pivotal Tracker Stories.
Home-page: https://github.com/xxihawkxx/pivotal_fetcher
Author: Chetan Bhatt
Author-email: ichetanbhatt@gmail.com
License: MIT License
Platform: UNKNOWN
Classifier: Intended Audience :: Developers
Classifier: License :: OSI Approved :: MIT License
Classifier: Operating System :: OS Independent
Classifier: Programming Language :: Python
